matEdgeGenerator/__init__.py
matEdgeGenerator/example.py
matEdgeGenerator/generator.py
matEdgeGenerator/lib.py
mat_edge_generator-0.5.6.dist-info/METADATA
mat_edge_generator-0.5.6.dist-info/WHEEL
mat_edge_generator-0.5.6.dist-info/top_level.txt
mat_edge_generator-0.5.6.dist-info/RECORD
