Metadata-Version: 2.1
Name: mat-edge-generator
Version: 0.5.6
Summary: This library is used for creating a MAT edge starting from a simple configuration file
Home-page: UNKNOWN
Author: Filippo Ghelfi
Author-email: f.ghelfi@40-factory.com
License: UNKNOWN
Platform: UNKNOWN
Requires-Dist: numpy
Requires-Dist: pyyaml
